countsy-1.0.9.dist-info/licenses/LICENSE
src/__init__.py
src/cli.py
src/counting.py
src/output_formatting.py
src/parsing.py
countsy-1.0.9.dist-info/METADATA
countsy-1.0.9.dist-info/WHEEL
countsy-1.0.9.dist-info/entry_points.txt
countsy-1.0.9.dist-info/top_level.txt
countsy-1.0.9.dist-info/RECORD
